group_imputer/__init__.py
group_imputer/group_imputer.py
group_imputer-0.0.2.dist-info/LICENSE
group_imputer-0.0.2.dist-info/METADATA
group_imputer-0.0.2.dist-info/WHEEL
group_imputer-0.0.2.dist-info/top_level.txt
group_imputer-0.0.2.dist-info/RECORD
