Metadata-Version: 2.1
Name: group-imputer
Version: 0.0.2
Summary: Null imputing utility - work in progress
Home-page: https://github.com/eliottkalfon/group-imputer
Author: Eliott Kalfon
Author-email: eliott.kalfon@gmail.com
License: UNKNOWN
Platform: UNKNOWN
Classifier: Programming Language :: Python :: 3
Classifier: License :: OSI Approved :: MIT License
Classifier: Operating System :: OS Independent
Requires-Python: >=3.6
